barn/__init__.py
barn/admin.py
barn/apps.py
barn/conf.py
barn/decorators.py
barn/models.py
barn/scheduler.py
barn/signals.py
barn/worker.py
barn/management/__init__.py
barn/management/commands/__init__.py
barn/management/commands/runworker.py
barn/migrations/0001_initial.py
barn/migrations/0002_schedule_interval.py
barn/migrations/__init__.py
task_barn-0.2.0.dist-info/LICENSE
task_barn-0.2.0.dist-info/METADATA
task_barn-0.2.0.dist-info/WHEEL
task_barn-0.2.0.dist-info/top_level.txt
task_barn-0.2.0.dist-info/RECORD
