Metadata-Version: 2.1
Name: task-barn
Version: 0.2.0
Summary: Lightweight scheduler and worker for Django using a database backend
License: MIT
Project-URL: Homepage, https://github.com/bibenga/barn-py
Project-URL: Issues, https://github.com/bibenga/barn-py/issues
Keywords: django,distributed,multiprocessing,task,scheduler
Classifier: Environment :: Web Environment
Classifier: Framework :: Django
Classifier: Intended Audience :: Developers
Classifier: License :: OSI Approved :: MIT License
Classifier: Operating System :: OS Independent
Classifier: Programming Language :: Python
Classifier: Programming Language :: Python :: 3
Classifier: Programming Language :: Python :: 3.10
Classifier: Programming Language :: Python :: 3.11
Classifier: Programming Language :: Python :: 3.12
Classifier: Topic :: Internet :: WWW/HTTP
Classifier: Topic :: System :: Distributed Computing
Classifier: Topic :: Software Development :: Libraries :: Python Modules
Requires-Python: >=3.10
License-File: LICENSE
Requires-Dist: django <6,>=5
Provides-Extra: croniter
Requires-Dist: croniter <3,>=2 ; extra == 'croniter'
Provides-Extra: test
Requires-Dist: pytest ; extra == 'test'
Requires-Dist: pytest-django ; extra == 'test'
Requires-Dist: pytest-mock ; extra == 'test'
Requires-Dist: pytest-asyncio ; extra == 'test'
Requires-Dist: psycopg[binary] ; extra == 'test'
